typechat/__about__.py
typechat/__init__.py
typechat/py.typed
typechat/_internal/__init__.py
typechat/_internal/interactive.py
typechat/_internal/model.py
typechat/_internal/result.py
typechat/_internal/translator.py
typechat/_internal/validator.py
typechat/_internal/ts_conversion/__init__.py
typechat/_internal/ts_conversion/python_type_to_ts_nodes.py
typechat/_internal/ts_conversion/ts_node_to_string.py
typechat/_internal/ts_conversion/ts_type_nodes.py
typechat-0.0.4.dist-info/METADATA
typechat-0.0.4.dist-info/WHEEL
typechat-0.0.4.dist-info/licenses/LICENSE
typechat-0.0.4.dist-info/RECORD
