Metadata-Version: 2.4
Name: typechat
Version: 0.0.4
Summary: TypeChat is a library that makes it easy to build natural language interfaces using types.
Project-URL: Documentation, https://github.com/microsoft/TypeChat#readme
Project-URL: Issues, https://github.com/microsoft/TypeChat/issues
Project-URL: Source, https://github.com/microsoft/TypeChat
Author: Microsoft Corporation
License-Expression: MIT
License-File: LICENSE
Classifier: Development Status :: 4 - Beta
Classifier: Programming Language :: Python
Classifier: Programming Language :: Python :: 3.11
Classifier: Programming Language :: Python :: 3.12
Classifier: Programming Language :: Python :: 3.13
Classifier: Programming Language :: Python :: Implementation :: CPython
Classifier: Programming Language :: Python :: Implementation :: PyPy
Requires-Python: >=3.11
Requires-Dist: httpx>=0.27.0
Requires-Dist: pydantic-core>=2.16.3
Requires-Dist: pydantic>=2.5.2
Requires-Dist: typing-extensions>=4.10.0
Provides-Extra: dev
Requires-Dist: coverage[toml]>=6.5; extra == 'dev'
Requires-Dist: pytest>=8.0.2; extra == 'dev'
Requires-Dist: syrupy>=4.6.1; extra == 'dev'
Provides-Extra: examples
Requires-Dist: python-dotenv>=1.0.0; extra == 'examples'
Requires-Dist: spotipy; extra == 'examples'
